apply_firewall.py
setup.py
apply_firewall.egg-info/PKG-INFO
apply_firewall.egg-info/SOURCES.txt
apply_firewall.egg-info/dependency_links.txt
apply_firewall.egg-info/entry_points.txt
apply_firewall.egg-info/top_level.txt