Metadata-Version: 1.0
Name: apply-firewall
Version: 1.0
Summary: A tool for applying iptables of linux safely, it rollbacks to
Home-page: UNKNOWN
Author: Victor Lin
Author-email: bornstub@gmail.com
License: UNKNOWN
Platform: UNKNOWN
